bigbrother/__init__.py
bigbrother/common.py
bigbrother/generic.py
bigbrother/builtins/__init__.py
bigbrother/builtins/dict.py
bigbrother/builtins/list.py
bigbrother/builtins/set.py
bigbrother/libraries/__init__.py
bigbrother/libraries/pydantic.py
bigbrother/tests/__init__.py
bigbrother/tests/common.py
bigbrother/tests/builtins/__init__.py
bigbrother/tests/builtins/test_dict.py
bigbrother/tests/builtins/test_list.py
bigbrother/tests/builtins/test_set.py
bigbrother/tests/libraries/__init__.py
bigbrother/tests/libraries/test_pydantic.py
bigbrother-0.1.3.dist-info/LICENSE
bigbrother-0.1.3.dist-info/METADATA
bigbrother-0.1.3.dist-info/WHEEL
bigbrother-0.1.3.dist-info/top_level.txt
bigbrother-0.1.3.dist-info/RECORD
