Metadata-Version: 2.1
Name: bigbrother
Version: 0.1.3
Summary: A library for object observability
Author-email: Tim Paine <t.paine154@gmail.com>
License: Apache License
Project-URL: Repository, https://github.com/timkpaine/bigbrother
Project-URL: Homepage, https://github.com/timkpaine/bigbrother
Keywords: observer,observer-pattern
Classifier: Development Status :: 3 - Alpha
Classifier: Programming Language :: Python :: Implementation :: CPython
Classifier: Programming Language :: Python :: Implementation :: PyPy
Classifier: Programming Language :: Python :: 3
Classifier: Programming Language :: Python :: 3.8
Classifier: Programming Language :: Python :: 3.9
Classifier: Programming Language :: Python :: 3.10
Classifier: Programming Language :: Python :: 3.11
Requires-Python: >=3.8
License-File: LICENSE
Requires-Dist: pydantic
Provides-Extra: develop
Requires-Dist: black (>=23) ; extra == 'develop'
Requires-Dist: bump2version ; extra == 'develop'
Requires-Dist: check-manifest ; extra == 'develop'
Requires-Dist: mypy ; extra == 'develop'
Requires-Dist: pytest ; extra == 'develop'
Requires-Dist: pytest-cov ; extra == 'develop'
Requires-Dist: ruff ; extra == 'develop'
Requires-Dist: semgrep ; extra == 'develop'
Requires-Dist: Sphinx ; extra == 'develop'
Requires-Dist: sphinx-markdown-builder ; extra == 'develop'
Requires-Dist: twine ; extra == 'develop'
Requires-Dist: wheel ; extra == 'develop'
Provides-Extra: test
Requires-Dist: pytest ; extra == 'test'
Requires-Dist: pytest-cov ; extra == 'test'
